{
	"$schema": "https://tonytools.win/schemas/dlge.schema.json",
	"hash": "[assembly:/localization/hitman6/conversations/island/29000_magpie/29000_handler/ds29011_oppvote_briefing.sweetdialog?/ds29011_oppvote_briefing_diana_001.sweetdialogitem].pc_dialogevent",
	"DITL": "00B7E83B2B5BFE20",
	"CLNG": "00E3CBB0725ED16C",
	"rootContainer": {
		"type": "WavFile",
		"wavName": "ds29011_oppvote_briefing_diana_001",
		"soundtag": "Voiceover_Handler_ICAEarpiece",
		"defaultWav": "[assembly:/sound/wwise/originals/voices/english(us)/island/29000_magpie/29000_handler/ds29011_oppvote_briefing_diana_001.wav].pc_wes",
		"defaultFfx": "[assembly:/_pro/facefx/exported_animation/english(us)/island/29000_magpie/29000_handler/ds29011_oppvote_briefing_diana_001.animset].pc_animset",
		"languages": {
			"en": "//(0,7.2)\\\\So. Sophia Washington has called a council meeting between the original five members of The Ark Society.//(7.2,9.5)\\\\Sophia hopes to pass some sort of motion,//(9.5,15.5)\\\\but she faces stark opposition from ultra-conservative coal baron, Jebediah Block.//(15.5,21.3)\\\\Hm. I suggest you find Mr. Block while the Council is still in recess, 47.//(21.3,26.2974)\\\\I suspect the headstrong Sophia will not take kindly to dissidents and troublemakers.",
			"fr": "//(0,2.944785)\\\\Sophia Washington a demandé une réunion du conseil//(2.944785,7.125767)\\\\entre les cinq membres originaux de la société de l'Arche.//(7.125767,10.04675)\\\\Elle espère faire passer une sorte de motion,//(10.04675,13.13914)\\\\mais un baron du charbon ultra-conservateur,//(13.13914,16.232)\\\\Jebediah Block, s'y oppose.//(16.232,21.62301)\\\\Je vous suggère de trouver ce M. Block tant que la séance est levée, 47.//(21.62301,24.68779)\\\\Sophia est autoritaire, j'imagine qu'elle ne tolérera pas//(24.68779,26.2974)\\\\qu'un électron libre lui tienne tête.",
			"it": "//(0,2.185232)\\\\Allora, Sophia Washington ha indetto un'assemblea//(2.185232,7)\\\\del consiglio coi cinque fondatori della Ark Society.//(7,12)\\\\Spera di far approvare una mozione ma deve vedersela con la dura opposizione di Jebediah Block,//(12,16)\\\\un magnate del carbone ultra conservatore.//(16,21.5)\\\\Mmm. Ti consiglio di trovare il signor Block finché il consiglio è ancora in pausa, 47.//(21.5,24)\\\\Ho il sospetto che Sophia e la sua testardaggine//(24,26.35896)\\\\non vedranno di buon occhio oppositori e piantagrane.",
			"de": "//(0,3.3)\\\\So. Sophia hat eine Ratsversammlung//(3.3,5.35)\\\\der ursprünglichen fünf Mitglieder//(5.35,7.15)\\\\der Ark-Gesellschaft einberufen.//(7.15,9.5)\\\\Sie will wohl eine Art Antrag durchsetzen,//(9.5,12.19669)\\\\aber bekommt mächtigen Gegenwind von Jebediah Block,//(12.19669,16)\\\\einem ultrakonservativen Kohlebaron.//(16,18.8)\\\\Hm. Ich würde vorschlagen, Sie finden Mr. Block,//(18.8,21.8)\\\\solange die Ratssitzung noch unterbrochen ist, 47.//(21.8,22.68563)\\\\Vermutlich geht die dickköpfige Sophia//(22.68563,24.82612)\\\\nicht gerade zimperlich mit Dissidenten//(24.82612,26.29739)\\\\und Querulanten um.",
			"es": "//(0,2.601633)\\\\Vale. Sophia Washington ha convocado una reunión//(2.601633,4.780468)\\\\del consejo entre los cinco miembros originales//(4.780468,6.448313)\\\\de la Ark Society.//(6.448313,8.72862)\\\\Sophia espera aprobar algún tipo de moción,//(8.72862,11.52998)\\\\pero se enfrenta a la dura oposición de Jebediah//(11.52998,13.92182)\\\\Block, un barón del carbón ultraconservador.//(13.92182,17.24745)\\\\Mmm... 47, te recomiendo que aproveches la pausa del//(17.24745,19.53782)\\\\consejo para encontrar al señor Block.//(19.53782,22.9617)\\\\Algo me dice que a esa cabezadura de Sophia no le//(22.9617,25.4518)\\\\gustan mucho ni los disidentes ni la gente//(25.4518,26.4518)\\\\problemática.",
			"ru": "//(0,3.916092)\\\\Итак. София Вашингтон созвала Совет с участием//(3.916092,7.363657)\\\\пяти самых первых членов «Общества Ковчега».//(7.363657,9.859024)\\\\Она хочет принять какую-то резолюцию,//(9.859024,11.73313)\\\\но ультраконсервативный угольный магнат//(11.73313,14.71217)\\\\Джебедая Блок категорически против этого.//(14.71217,17.84395)\\\\Хм. Советую найти мистера Блока,//(17.84395,20.33932)\\\\пока в заседании объявлен перерыв,//(20.33932,24.25541)\\\\47-й. Наверняка своенравная София терпеть не может//(24.25541,26.2974)\\\\диссидентов и смутьянов.",
			"cn": "//(0,7.207)\\\\所以。索菲娅·华盛顿召集了方舟会最初的五名成员进行理事会议。//(7.207,15.69)\\\\索菲娅希望能通过某项议案，但她要面对的是相当守旧的煤炭大亨，耶比迪·布洛克。//(15.69,21.552)\\\\嗯。我建议你在议会休息时找到布洛克先生，47。//(21.552,26.297)\\\\我估计顽固的索菲娅对异议者和闹事的家伙不会手软。",
			"tc": "//(0,7.1)\\\\所以。索菲婭．華盛頓召集方舟會最初的五名成員進行理事會議。//(7.1,15.9)\\\\索菲婭希望能通過某項議案，但她要面對的是相當守舊的煤炭大亨，耶比迪．布洛克。//(15.9,21.5)\\\\嗯。我建議你議會休息時找到布洛克先生，47。//(21.5,26.2974)\\\\我猜頑固的索菲婭對異議者和鬧事的傢伙不會手軟。",
			"jp": "//(0,2)\\\\ソフィア・ワシントンは//(2,7.5)\\\\アーク・ソサエティの5人の初期メンバーを招集して評議会を開いたわ。//(7.5,10.5)\\\\ソフィアは何らかの議案を通すつもりでいるらしいけど、//(10.5,16)\\\\超保守的な炭鉱王ジェベディア・ブロックに真っ向から対立されている。//(16,21.5)\\\\ふむ、評議会の休会中にブロック氏を探すのよ、47。//(21.5,23.5)\\\\あの強情なソフィアは、//(23.5,26.2974)\\\\自分と対立する者や厄介者相手に行儀よくするはずないわ。"
		}
	}
}
