{
    "$schema": "https://tonytools.win/schemas/dlge.schema.json",
    "hash": "[assembly:/localization/hitman6/conversations/italy/1000_elusive/1000_4xrumandcoke/1000_4xrumandcoke_story/dr1657_touristanecdotes.sweetdialog?/dr1657_touristanecdotes_tourist_et_001.sweetdialogitem].pc_dialogevent",
    "DITL": "00B7E83B2B5BFE20",
    "CLNG": "00E3CBB0725ED16C",
    "rootContainer": {
        "type": "WavFile",
        "wavName": "dr1657_touristanecdotes_tourist_et_001",
        "soundtag": "In-world_Mission_Normal",
        "defaultWav": "[assembly:/sound/wwise/originals/voices/english(us)/italy/1000_elusive/1000_4xrumandcoke/1000_4xrumandcoke_story/dr1657_touristanecdotes_tourist_et_001.wav].pc_wes",
        "defaultFfx": "[assembly:/_pro/facefx/exported_animation/english(us)/italy/1000_elusive/1000_4xrumandcoke/1000_4xrumandcoke_story/dr1657_touristanecdotes_tourist_et_001.animset].pc_animset",
        "languages": {
            "en": "//(0,30)\\\\Gary Busey just told me he used to be a pitcher for the Cubs, but wasn’t that a movie?",
            "fr": "//(0,30)\\\\Gary Busey a dit qu'il avait été lanceur pour les Cubs, mais c'était dans un film, non ?",
            "it": "//(0,30)\\\\Gary Busey mi ha appena detto che una volta era un lanciatore dei Cubs... Ma non era un film?",
            "de": "//(0,30)\\\\Gary Busey hat gerade erzählt, dass er mal Werfer für die Cubs war, aber war das nicht in einem Film?",
            "es": "//(0,30)\\\\Gary Busey acaba de decir que solía ser lanzador de los Cubs, ¿pero eso no era en una peli?",
            "ru": "//(0,4)\\\\Гэри Бьюзи только что сказал, что был питчером в «Чикаго Кабс».//(4,34)\\\\Но, по-моему, это в кино было, нет?",
            "cn": "//(0,30)\\\\加里·布西刚刚告诉我，他曾经是小熊队的投手，但那不是一部电影吗？",
            "tc": "//(0,30)\\\\蓋瑞．布希剛剛告訴我他曾經是小熊隊的投手，不過那不是一部電影嗎？",
            "jp": "//(0,30)\\\\ゲイリー・ビジーが、 カブスの ピッチャーを 経験したって 言った。 でもそれって 映画だよな？"
        }
    }
}
