{
	"$schema": "https://tonytools.win/schemas/dlge.schema.json",
	"hash": "[assembly:/localization/hitman6/conversations/italy/1000_virus/1000_handler/ds1024_carusodown.sweetdialog?/ds1024_carusodown_diana_001.sweetdialogitem].pc_dialogevent",
	"DITL": "00B7E83B2B5BFE20",
	"CLNG": "00E3CBB0725ED16C",
	"rootContainer": {
		"type": "WavFile",
		"wavName": "ds1024_carusodown_diana_001",
		"soundtag": "Voiceover_Handler_ICAEarpiece",
		"defaultWav": "[assembly:/sound/wwise/originals/voices/english(us)/italy/1000_virus/1000_handler/ds1024_carusodown_diana_001.wav].pc_wes",
		"defaultFfx": "[assembly:/_pro/facefx/exported_animation/english(us)/italy/1000_virus/1000_handler/ds1024_carusodown_diana_001.animset].pc_animset",
		"languages": {
			"en": "//(0,30)\\\\Target down. Next up, Francesca De Santis.",
			"fr": "//(0,30)\\\\Cible éliminée. Passez à la suivante, Francesca De Santis.",
			"it": "//(0,30)\\\\Bersaglio eliminato. Passiamo a Francesca De Santis.",
			"de": "//(0,1.186196)\\\\Ziel neutralisiert.//(1.186196,31.1862)\\\\Kümmern Sie sich jetzt um Francesca De Santis.",
			"es": "//(0,1.002)\\\\Objetivo eliminado.//(1.002,31.002)\\\\La siguiente es Francesca De Santis.",
			"ru": "//(0,30)\\\\Цель уничтожена. Теперь — Франческа Де Сантис.",
			"cn": "//(0,1.1)\\\\目标已被消灭。//(1.1,31.1)\\\\接下来是弗兰西斯卡·德·桑蒂斯。",
			"tc": "//(0,30)\\\\目標已倒下。接下來是弗蘭西斯卡．德．桑蒂斯。",
			"jp": "//(0,30)\\\\ターゲット・ダウン。次はフランチェスカ・デ・サンティスよ。"
		}
	}
}
