{
	"$schema": "https://tonytools.win/schemas/dlge.schema.json",
	"hash": "00CBDB3A12858D21",
	"DITL": "005CC166F7715F6D",
	"CLNG": "00063B34B5153AEE",
	"rootContainer": {
		"type": "Random",
		"containers": [
			{
				"type": "WavFile",
				"wavName": "ds20046_sp_maisonescaping_diana_001",
				"weight": 0.12499994784593271,
				"soundtag": "Voiceover_Handler_ICAEarpiece",
				"defaultWav": "[assembly:/sound/wwise/originals/voices/english(us)/austria/20000_hawk/20000_handler/ds20046_sp_maisonescaping_diana_001.wav].pc_wes",
				"defaultFfx": "[assembly:/_pro/facefx/exported_animation/english(us)/austria/20000_hawk/20000_handler/ds20046_sp_maisonescaping_diana_001.animset].pc_animset",
				"languages": {
					"en": "//(0,30)\\\\47, you need to stop Maison. He’s trying to get away.",
					"fr": "//(0,30)\\\\47, vous devez arrêter Maison. Il essaie de s'échapper.",
					"it": "//(0,30)\\\\47, devi fermare Maison. Sta cercando di andarsene.",
					"de": "//(0,30)\\\\47, Sie müssen Maison aufhalten. Er versucht wegzukommen.",
					"es": "//(0,30)\\\\47, debes detener a Maison. Está intentando huir.",
					"ru": "//(0,30)\\\\47-й, останови МЕЗОНА. Он пытается сбежать.",
					"cn": "//(0,30)\\\\47，你得阻止米森。他想逃跑。",
					"tc": "//(0,30)\\\\47，你得阻止梅森。他正在試圖逃走。",
					"jp": "//(0,30)\\\\47、メゾンを止めて。逃げようとしているわ。"
				}
			},
			{
				"type": "WavFile",
				"wavName": "ds20046_sp_maisonescaping_diana_002",
				"weight": 0.12499994784593271,
				"soundtag": "Voiceover_Handler_ICAEarpiece",
				"defaultWav": "[assembly:/sound/wwise/originals/voices/english(us)/austria/20000_hawk/20000_handler/ds20046_sp_maisonescaping_diana_002.wav].pc_wes",
				"defaultFfx": "[assembly:/_pro/facefx/exported_animation/english(us)/austria/20000_hawk/20000_handler/ds20046_sp_maisonescaping_diana_002.animset].pc_animset",
				"languages": {
					"en": "//(0,30)\\\\Maison is heading for the exit, 47. If you don’t stop him now, it’s all over.",
					"fr": "//(0,30)\\\\Maison essaie de rejoindre la sortie, 47. Tout sera perdu si vous ne l'arrêtez pas maintenant.",
					"it": "//(0,30)\\\\Maison sta raggiungendo l'uscita, 47. Se non lo fermi, sarà tutto perduto.",
					"de": "//(0,30)\\\\Maison ist auf dem Weg zum Ausgang, 47. Wenn Sie ihn nicht aufhalten, ist alles vorbei.",
					"es": "//(0,30)\\\\Maison se dirige hacia la salida, 47. Si no lo detienes ahora, habremos fracasado.",
					"ru": "//(0,30)\\\\МЕЗОН направляется к выходу, 47-й. Если ты его не остановишь, всё пропало.",
					"cn": "//(0,30)\\\\47，米森正在前往出口。如果你不立刻阻止他，一切就完了。",
					"tc": "//(0,30)\\\\梅森正走向出口，47。你不阻止他的話就完了。",
					"jp": "//(0,30)\\\\メゾンが出口に向かっているわ。止められなかったら終わりよ。"
				}
			},
			{
				"type": "WavFile",
				"wavName": "ds20046_sp_maisonescaping_diana_003",
				"weight": 0.12499994784593271,
				"soundtag": "Voiceover_Handler_ICAEarpiece",
				"defaultWav": "[assembly:/sound/wwise/originals/voices/english(us)/austria/20000_hawk/20000_handler/ds20046_sp_maisonescaping_diana_003.wav].pc_wes",
				"defaultFfx": "[assembly:/_pro/facefx/exported_animation/english(us)/austria/20000_hawk/20000_handler/ds20046_sp_maisonescaping_diana_003.animset].pc_animset",
				"languages": {
					"en": "//(0,30)\\\\47, be aware. Maison is on to you and is trying to leave the area.",
					"fr": "//(0,30)\\\\Faites attention, 47. Maison vous a repéré et essaie de fuir le manoir.",
					"it": "//(0,30)\\\\47, fai attenzione. Maison sa che sei qui e sta cercando di andarsene.",
					"de": "//(0,30)\\\\47, passen Sie auf. Maison ist Ihnen auf die Schliche gekommen und versucht, das Gebiet zu verlassen.",
					"es": "//(0,30)\\\\Ten cuidado, 47. Maison te ha descubierto e intenta abandonar la zona.",
					"ru": "//(0,30)\\\\47-й, будь начеку. МЕЗОН заметил тебя и пытается покинуть периметр.",
					"cn": "//(0,30)\\\\47，注意。米森盯上你了，正在逃离此区域。",
					"tc": "//(0,30)\\\\47，注意了。梅森正在試圖離開此區域。",
					"jp": "//(0,30)\\\\47、気を付けて。メゾンが気付いて逃げようとしているわ。"
				}
			},
			{
				"type": "WavFile",
				"wavName": "ds20046_sp_maisonescaping_diana_004",
				"weight": 0.12499994784593271,
				"soundtag": "Voiceover_Handler_ICAEarpiece",
				"defaultWav": "[assembly:/sound/wwise/originals/voices/english(us)/austria/20000_hawk/20000_handler/ds20046_sp_maisonescaping_diana_004.wav].pc_wes",
				"defaultFfx": "[assembly:/_pro/facefx/exported_animation/english(us)/austria/20000_hawk/20000_handler/ds20046_sp_maisonescaping_diana_004.animset].pc_animset",
				"languages": {
					"en": "//(0,30)\\\\47, Guillaume Maison is attempting an evacuation. Stop him.",
					"fr": "//(0,30)\\\\47, Guillaume Maison essaie de quitter le domaine. Attrapez-le avant.",
					"it": "//(0,30)\\\\47, Guillaume Maison sta tentando di fuggire. Fermalo.",
					"de": "//(0,30)\\\\47, Guillaume Maison versucht, eine Evakuierung einzuleiten. Halten Sie ihn auf.",
					"es": "//(0,30)\\\\47, Guillaume Maison está intentando salir de la zona. Evítalo.",
					"ru": "//(0,30)\\\\47-й, ГИЙОМ МЕЗОН пытается уйти. Останови его.",
					"cn": "//(0,30)\\\\47，吉奥姆·米森正企图撤离。别让他得逞。",
					"tc": "//(0,30)\\\\47，紀堯姆．梅森正在試圖撤離。阻止他。",
					"jp": "//(0,30)\\\\47、ギヨーム・メゾンが非難しようとしているわ。彼を止めて。"
				}
			},
			{
				"type": "WavFile",
				"wavName": "ds20046_sp_maisonescaping_diana_005",
				"weight": 0.12499994784593271,
				"soundtag": "Voiceover_Handler_ICAEarpiece",
				"defaultWav": "[assembly:/sound/wwise/originals/voices/english(us)/austria/20000_hawk/20000_handler/ds20046_sp_maisonescaping_diana_005.wav].pc_wes",
				"defaultFfx": "[assembly:/_pro/facefx/exported_animation/english(us)/austria/20000_hawk/20000_handler/ds20046_sp_maisonescaping_diana_005.animset].pc_animset",
				"languages": {
					"en": "//(0,30)\\\\Maison is attempting to leave. You have to stop him, 47.",
					"fr": "//(0,30)\\\\Maison tente de s'échapper. Empêchez-le, 47.",
					"it": "//(0,30)\\\\Maison sta cercando di scappare. Devi fermarlo, 47.",
					"de": "//(0,30)\\\\Maison will sich verziehen. Sie müssen ihn aufhalten, 47.",
					"es": "//(0,30)\\\\Maison está intentando irse. Tienes que detenerlo, 47.",
					"ru": "//(0,30)\\\\МЕЗОН пытается сбежать. Ты должен его остановить, 47-й.",
					"cn": "//(0,30)\\\\米森企图逃跑。47，你得阻止他。",
					"tc": "//(0,30)\\\\梅森正在試圖離開。你得阻止他，47。",
					"jp": "//(0,30)\\\\メゾンが逃げようとしているわ。必ず止めるのよ。"
				}
			},
			{
				"type": "WavFile",
				"wavName": "ds20046_sp_maisonescaping_diana_006",
				"weight": 0.12499994784593271,
				"soundtag": "Voiceover_Handler_ICAEarpiece",
				"defaultWav": "[assembly:/sound/wwise/originals/voices/english(us)/austria/20000_hawk/20000_handler/ds20046_sp_maisonescaping_diana_006.wav].pc_wes",
				"defaultFfx": "[assembly:/_pro/facefx/exported_animation/english(us)/austria/20000_hawk/20000_handler/ds20046_sp_maisonescaping_diana_006.animset].pc_animset",
				"languages": {
					"en": "//(0,30)\\\\I'm tracking Maison. He's heading for an exit, 47.",
					"fr": "//(0,30)\\\\Je poursuis Maison. Il se dirige vers une sortie, 47.",
					"it": "//(0,30)\\\\Ho individuato Maison. Si sta dirigendo verso un'uscita, 47.",
					"de": "//(0,30)\\\\Ich verfolge Maison. Er ist auf dem Weg zu einem Ausgang, 47.",
					"es": "//(0,30)\\\\Estoy siguiendo a Maison. Se dirige hacia la salida, 47.",
					"ru": "//(0,30)\\\\Слежу за МЕЗОНОМ. Он направляется к выходу, 47-й.",
					"cn": "//(0,30)\\\\我正在追踪米森。47，他正在前往出口。",
					"tc": "//(0,30)\\\\我在追蹤梅森。他正走向出口，47。",
					"jp": "//(0,30)\\\\メゾンが出口に向かっているわ。"
				}
			},
			{
				"type": "WavFile",
				"wavName": "ds20046_sp_maisonescaping_diana_007",
				"weight": 0.12499994784593271,
				"soundtag": "Voiceover_Handler_ICAEarpiece",
				"defaultWav": "[assembly:/sound/wwise/originals/voices/english(us)/austria/20000_hawk/20000_handler/ds20046_sp_maisonescaping_diana_007.wav].pc_wes",
				"defaultFfx": "[assembly:/_pro/facefx/exported_animation/english(us)/austria/20000_hawk/20000_handler/ds20046_sp_maisonescaping_diana_007.animset].pc_animset",
				"languages": {
					"en": "//(0,30)\\\\Maison is moving fast. I think he's heading for an exit.",
					"fr": "//(0,30)\\\\Maison est en train de courir. Je pense qu'il cherche une issue.",
					"it": "//(0,30)\\\\Maison si sta muovendo rapidamente. Penso che stia andando verso un'uscita.",
					"de": "//(0,30)\\\\Maison hat es äußerst eilig. Ich glaube, er will zu einem Ausgang.",
					"es": "//(0,30)\\\\Maison se mueve con rapidez. Creo que se dirige hacia una salida.",
					"ru": "//(0,30)\\\\МЕЗОН движется быстро. Думаю, он направляется к выходу.",
					"cn": "//(0,30)\\\\米森动作很快。他应该正在前往出口。",
					"tc": "//(0,30)\\\\梅森正在快速行動。我看他正走向出口。",
					"jp": "//(0,30)\\\\メゾンがすごいスピードで移動している。出口に向かってるんだわ。"
				}
			},
			{
				"type": "WavFile",
				"wavName": "ds20046_sp_maisonescaping_diana_008",
				"weight": 0.12499994784593271,
				"soundtag": "Voiceover_Handler_ICAEarpiece",
				"defaultWav": "[assembly:/sound/wwise/originals/voices/english(us)/austria/20000_hawk/20000_handler/ds20046_sp_maisonescaping_diana_008.wav].pc_wes",
				"defaultFfx": "[assembly:/_pro/facefx/exported_animation/english(us)/austria/20000_hawk/20000_handler/ds20046_sp_maisonescaping_diana_008.animset].pc_animset",
				"languages": {
					"en": "//(0,30)\\\\47, you need to focus on Maison. He's attempting to leave the mansion area.",
					"fr": "//(0,30)\\\\Concentrez-vous sur Maison, 47. Il essaie de quitter le domaine.",
					"it": "//(0,30)\\\\47, devi concentrarti su Maison. Sta cercando di abbandonare l'area della villa.",
					"de": "//(0,30)\\\\47, Sie müssen sich auf Maison konzentrieren. Er versucht, das Gelände des Herrenhauses zu verlassen.",
					"es": "//(0,30)\\\\47, debes concentrarte en Maison. Pretende abandonar la zona de la mansión.",
					"ru": "//(0,30)\\\\47-й, сконцентрируйся на МЕЗОНЕ. Он пытается покинуть особняк.",
					"cn": "//(0,30)\\\\47，你得专心对付米森。他正企图离开庄园区域。",
					"tc": "//(0,30)\\\\47，你得全力阻止梅森。他正在嘗試離開豪宅區域。",
					"jp": "//(0,30)\\\\47、メゾンに注意して。屋敷を出ようとしているわ。"
				}
			}
		]
	}
}
