{
	"$schema": "https://tonytools.win/schemas/dlge.schema.json",
	"hash": "[assembly:/localization/hitman6/conversations/caged/32500_falcon/ds32506_sp_reznikovfail.sweetdialog?/ds32506_sp_reznikovfail_diana_001.sweetdialogitem].pc_dialogevent",
	"DITL": "00B7E83B2B5BFE20",
	"CLNG": "00E3CBB0725ED16C",
	"rootContainer": {
		"type": "WavFile",
		"wavName": "ds32506_sp_reznikovfail_diana_001",
		"soundtag": "Voiceover_Handler_ICAEarpiece",
		"defaultWav": "[assembly:/sound/wwise/originals/voices/english(us)/caged/32500_falcon/ds32506_sp_reznikovfail_diana_001.wav].pc_wes",
		"defaultFfx": "[assembly:/_pro/facefx/exported_animation/english(us)/caged/32500_falcon/ds32506_sp_reznikovfail_diana_001.animset].pc_animset",
		"languages": {
			"en": "//(0,30)\\\\Vitaly Reznikov had managed to get away. The mission is over, 47.",
			"fr": "//(0,30)\\\\Vitaly Reznikov a réussi à s'en tirer. La mission est terminée, 47.",
			"it": "//(0,30)\\\\Vitaly Reznikov è riuscito ad andarsene. La missione è finita, 47.",
			"de": "//(0,30)\\\\Vitali Reznikov konnte entwischen. Die Mission ist vorbei, 47.",
			"es": "//(0,30)\\\\Vitaly Reznikov ha logrado huir. Se cancela la misión, 47.",
			"ru": "//(0,30)\\\\Виталию Резникову удалось скрыться. Задание отменяется, 47-й.",
			"cn": "//(0,30)\\\\维塔利·列兹尼科夫已设法逃离。47，任务结束。",
			"tc": "//(0,30)\\\\維大力‧雷茲尼克瓦成功逃脫了。任務結束了，47。",
			"jp": "//(0,30)\\\\ヴィタリ・レズニコフに逃げられたわ。任務はお終いよ、47。"
		}
	}
}
