{
	"$schema": "https://tonytools.win/schemas/dlge.schema.json",
	"hash": "[assembly:/localization/hitman6/conversations/miami/21000_flamingo/21000_handler/ds21079_thestig.sweetdialog?/ds21079_thestig_diana_002.sweetdialogitem].pc_dialogevent",
	"DITL": "00B7E83B2B5BFE20",
	"CLNG": "00E3CBB0725ED16C",
	"rootContainer": {
		"type": "WavFile",
		"wavName": "ds21079_thestig_diana_002",
		"soundtag": "Voiceover_Handler_ICAEarpiece",
		"defaultWav": "[assembly:/sound/wwise/originals/voices/english(us)/miami/21000_flamingo/21000_handler/ds21079_thestig_diana_002.wav].pc_wes",
		"defaultFfx": "[assembly:/_pro/facefx/exported_animation/english(us)/miami/21000_flamingo/21000_handler/ds21079_thestig_diana_002.animset].pc_animset",
		"languages": {
			"en": "//(0,3.465213)\\\\Some say he could make it as a top fashion model//(3.465213,6.930426)\\\\and that he is the only person to have ever visited//(6.930426,9.878482)\\\\the Palais de Walewska dressed as a vampire.//(9.878482,11.24126)\\\\All we know is,//(11.24126,12.50133)\\\\his name is 47!",
			"fr": "//(0,3.428)\\\\On raconte qu'il peut percer en tant que mannequin,//(3.428,7.47132)\\\\et qu'il est le seul à avoir visité le Palais de//(7.47132,9.440907)\\\\Walewska déguisé en vampire.//(9.440907,11.03104)\\\\Tout ce qu'on sait,//(11.03104,12.50133)\\\\c'est qu'il s'appelle 47 !",
			"it": "//(0,2.626676)\\\\Dicono che potrebbe fare il modello di haute//(2.626676,5.581685)\\\\couture e che sia l'unica persona ad aver mai//(5.581685,7.880026)\\\\visitato il Palais de Walewska travestito da//(7.880026,11.07034)\\\\vampiro. Tutto quello che sappiamo è che...//(11.07034,12.50133)\\\\si chiama 47.",
			"de": "//(0,0.8808788)\\\\Manche sagen,//(0.8808788,3.531847)\\\\er hätte das Zeug zum internationalen Mode-Model//(3.531847,5.548855)\\\\und er wäre der Einzige,//(5.548855,8.578532)\\\\der den Palais de Walewska als Vampir verkleidet//(8.578532,12.50133)\\\\besucht hat. Wir wissen nur eines: Sein Name ist 47!",
			"es": "//(0,2.807536)\\\\Hay quien dice que podría ganarse la vida como//(2.807536,5.92702)\\\\modelo de pasarela y es la única persona que ha//(5.92702,8.846337)\\\\visitado el Palais de Walewska vestido de vampiro.//(8.846337,10.51786)\\\\Lo único que sabemos...//(10.51786,12.50133)\\\\es que se llama 47.",
			"ru": "//(0,3.720519)\\\\Говорят, что он мог бы сделать карьеру в модельном//(3.720519,5.845276)\\\\бизнесе и что он единственный,//(5.845276,9.179754)\\\\кто посетил дворец Валевской в образе вампира.//(9.179754,10.90557)\\\\Мы знаем только то,//(10.90557,12.50133)\\\\что его зовут 47-й!",
			"cn": "//(0,8.125867)\\\\有人说他能成为顶尖的时装模特，且他曾打扮成吸血鬼访问过威利乌斯卡宫，而世界上再没有//(8.125867,12.50133)\\\\第二个人做过这种事。我们只知道，他的名字叫47！",
			"tc": "//(0,12.50133)\\\\聽說他是唯一一名能夠成為頂尖時尚模特兒的人並且也是唯一一名以吸血鬼身分造訪瓦留斯卡宮的人。我們只知道，他的名字是47！",
			"jp": "//(0,12.50133)\\\\彼はトップファッションモデルになりきることも、吸血鬼に扮してワレウスカ宮殿を訪れた唯一の人間であるとも言われている。彼について知っていることはただ1つ、その名は47！"
		}
	}
}
