{
  "$schema": "https://tonytools.win/schemas/dlge.schema.json",
  "hash": "[assembly:/localization/hitman6/conversations/paris/3000_elusive/3000_margerita/3000_margerita_story/dr3645_moxonentrancephone.sweetdialog?/dr3645_moxonentrancephone_moxon_et_001.sweetdialogitem].pc_dialogevent",
  "DITL": "00B7E83B2B5BFE20",
  "CLNG": "00E3CBB0725ED16C",
  "rootContainer": {
    "type": "WavFile",
    "wavName": "dr3645_moxonentrancephone_moxon_et_001",
    "soundtag": "In-world_Mission_Normal",
    "defaultWav": "[assembly:/sound/wwise/originals/voices/english(us)/paris/3000_elusive/3000_margerita/3000_margerita_story/dr3645_moxonentrancephone_moxon_et_001.wav].pc_wes",
    "defaultFfx": "[assembly:/_pro/facefx/exported_animation/english(us)/paris/3000_elusive/3000_margerita/3000_margerita_story/dr3645_moxonentrancephone_moxon_et_001.animset].pc_animset",
    "languages": {
      "en": "//(0,1.63)\\\\Moxon here.//(3,7.8)\\\\Vogt is delayed? Well, how much does he want the painting?//(7.8,10.55)\\\\I have plenty of other clients who are interested.//(11.05,12.95)\\\\No, no, that’s not good enough.//(12.95,16.4)\\\\If he wants the painting, he should stop wasting my time!//(16.4,19.2)\\\\I flew all the way over from Beacon Hill.//(20.2,24.57098)\\\\Yes, I know it’s quaint, that’s why I bought it!//(24.57098,29.03055)\\\\You tell Mr. Vogt that if he’s a no-show, I will go to the next buyer.//(29.03055,59.03055)\\\\You have 10 minutes. Good evening to you.",
      "fr": "//(0,1.2)\\\\Moxon, j'écoute.//(3.2,7.7)\\\\Vogt est en retard ? Eh bien, à quel point tient-il à ce tableau ?//(7.7,9.9)\\\\J'ai beaucoup d'autres clients intéressés.//(11,16.2)\\\\Non, non, ce n'est pas suffisant. S'il veut le tableau, qu'il arrête de me faire perdre mon temps !//(16.2,18.6)\\\\J'ai fait spécifiquement le voyage depuis Beacon Hill...//(20.2,23.7)\\\\Oui, je sais qu'il est \"charmant\" ; c'est bien pour ça que je l'ai acheté !//(24.9,54.9)\\\\Dites à M. Vogt que s'il ne vient pas, je contacterai l'acheteur suivant. Vous avez 10 minutes. Bonsoir.",
      "it": "//(0,1.736196)\\\\Sono Moxon.//(3.086196,7.56908)\\\\Vogt è in ritardo? Insomma, vuole davvero quel quadro?//(7.56908,10.86387)\\\\Perché ho una fila di clienti interessati all'acquisto.//(10.86387,16.59534)\\\\No, no, non ci siamo. Se vuole il quadro, deve piantarla di farmi perdere tempo!//(16.59534,20.07203)\\\\Sono venuto in aereo da Beacon Hill...//(20.07203,24.6092)\\\\Sì, lo so che è bizzarro e antiquato. L'ho comprato per questo!//(24.6092,28.92067)\\\\Riferisca al signor Vogt che, se non si presenta, mi rivolgerò a un altro compratore.//(28.92067,32.49736)\\\\Avete dieci minuti. Buona serata a lei.",
      "de": "//(0,1.686196)\\\\Moxon hier.//(3.036196,4.686196)\\\\Vogt verspätet sich?//(5.236196,7.355)\\\\Und Sie sind sicher, er will das Gemälde?//(7.355,9.763865)\\\\Ich hab nämlich noch andere Interessenten.//(11.01387,12.944)\\\\Nein, nein, das reicht nicht.//(12.944,16.50153)\\\\Wenn er das Gemälde will, soll er aufhören, meine Zeit zu verschwenden!//(16.50153,19.74632)\\\\Ich bin extra aus Beacon Hill hierher ...//(19.74632,23.6716)\\\\Ja, ich weiß, dass es grandios ist. Darum hab ich es ja gekauft!//(23.6716,28.965)\\\\Sagen Sie Mr Vogt, wenn er nicht kommt, rufe ich den nächsten Käufer an.//(28.965,58.965)\\\\Sie haben 10 Minuten. Wiederhören.",
      "es": "//(0,1.3)\\\\Soy Moxon.//(3.3,9.7)\\\\¿Vogt llega tarde? Bueno, ¿cuánto quiere el cuadro? Tengo muchos clientes que están interesados.//(10.9,16.35)\\\\No, no, eso no basta. ¡Si quiere el cuadro, debería evitar que pierda el tiempo!//(16.35,18.4)\\\\He venido en avión desde Beacon Hill...//(20.1,23)\\\\Sí, sé que es peculiar, ¡por eso lo compré!//(24.6,54.6)\\\\Dile al señor Vogt que, si no aparece, iré a por el siguiente comprador. Tienes 10 minutos. Buenas noches.",
      "ru": "//(0,3.3)\\\\Моксон.//(3.3,5.6)\\\\Фогт задерживается?//(5.6,8)\\\\Ему что, не нужна эта картина?//(8,11)\\\\У меня полно других покупателей.//(11,13)\\\\Нет, нет, этого недостаточно.//(13,16.4)\\\\Если он хочет картину, пусть прекращает тянуть время!//(16.4,20.2)\\\\Я летел сюда аж из Бостона...//(20.2,24.8)\\\\Да, я знаю, что она необычная! Поэтому я ее и купил!//(24.8,29.2)\\\\Передайте мистеру Фогту, что если он не явится, я звоню другому покупателю.//(29.2,59.2)\\\\У вас 10 минут. Хорошего вам вечера.",
      "cn": "//(0,1.63)\\\\我是莫克森。//(3,7.8)\\\\沃格特的航班延迟了？那么，他愿意为这幅画作付多少钱呢？//(7.8,10.55)\\\\我还有很多其他感兴趣的客戶呢。//(11.05,12.95)\\\\不，不行，那样不够好。//(12.95,16.4)\\\\如果他想要这幅画，就别再浪费我的时间了！//(16.4,19.2)\\\\我大老远从比肯山飞来。//(20.2,24.751)\\\\对的，我知道这很别致，所以我才会买下它！//(24.751,29.031)\\\\你告诉沃格特先生，要是他還沒有現身，我就去找下一名买家了。//(29.031,59.031)\\\\你还有十分钟的时间，晚上好呢。",
      "tc": "//(0,1.63)\\\\我是莫克森。//(3,7.8)\\\\沃格特的航班延遲了？那麼，他願意為這幅畫作付多少錢呢？//(7.8,10.55)\\\\我還有很多其他感興趣的客户呢。//(11.05,12.95)\\\\不，不行，那樣不夠好。//(12.95,16.4)\\\\如果他想要這幅畫，就別再浪費我的時間了！//(16.4,19.2)\\\\我大老遠從比肯山飛來。//(20.2,24.751)\\\\是的，我知道這很別緻，所以我才會買下它！//(24.751,29.031)\\\\你告訴沃格特先生，要是他還沒有現身，我就去找下一名買家了。//(29.031,59.031)\\\\你還有十分鐘的時間，晚上好呢。",
      "jp": "//(0,9.261061)\\\\モクソンだ。 ヴォグトが 遅れてる？ 彼は 本当に絵が 欲しいのか？ 興味を 持って いる顧客は 他にも//(9.261061,16.66991)\\\\たくさんいるんだ。 だめだ、 それじゃ 認められない。 絵が 欲しいなら、 さっさと会いに 来るんだ！//(16.66991,22.22654)\\\\こっちは わざわざビーコンヒルから 来てるんだぞ。 ああ、 もちろんユニークな絵さ、 だから買ったんだ！//(22.22654,30.5615)\\\\ヴォグト氏に 伝えろ、 10分以内に 来なければ、 別の バイヤーの ところへ 行くとな。 それじゃ。"
    }
  }
}